forager.py
models/__init__.py
models/alpine.py
models/date.py
models/hashforest.py
models/maple.py
models/palm.py
util/__init__.py
util/parser.py
util/payload.py
util/test.py
forager_toolkit-1.0.3.dist-info/LICENSE.txt
forager_toolkit-1.0.3.dist-info/METADATA
forager_toolkit-1.0.3.dist-info/WHEEL
forager_toolkit-1.0.3.dist-info/entry_points.txt
forager_toolkit-1.0.3.dist-info/top_level.txt
forager_toolkit-1.0.3.dist-info/RECORD
