Metadata-Version: 2.1
Name: forager-toolkit
Version: 1.0.3
Summary: A network traffic classification toolkit
Home-page: https://github.com/mayakapoor/forager
Author: Maya Kapoor
Author-email: mkapoor1@uncc.edu
Project-URL: Bug Tracker, https://github.com/mayakapoor/forager/issues
Project-URL: Documentation, https://forager-toolkit.readthedocs.io/en/latest/
Classifier: Programming Language :: Python :: 3
Classifier: License :: OSI Approved :: MIT License
Classifier: Operating System :: OS Independent
Requires-Python: >=3.6
License-File: LICENSE.txt
Requires-Dist: tapcap
Requires-Dist: rexactor
